PythonDebuggerTools/__init__.py
PythonDebuggerTools/logger.py
PythonDebuggerTools-0.0.18.dist-info/LICENSE
PythonDebuggerTools-0.0.18.dist-info/METADATA
PythonDebuggerTools-0.0.18.dist-info/WHEEL
PythonDebuggerTools-0.0.18.dist-info/top_level.txt
PythonDebuggerTools-0.0.18.dist-info/RECORD
