Metadata-Version: 2.1
Name: PythonDebuggerTools
Version: 0.0.18
Summary: A collection of useful debugging tools
Home-page: https://github.com/Luna-Cake/Logger
Author: Aakash Haran
Author-email: aakash.haran01@gmail.com
Project-URL: Bug Tracker, https://github.com/Luna-Cake/Logger
Classifier: Programming Language :: Python :: 3
Classifier: License :: OSI Approved :: MIT License
Classifier: Operating System :: OS Independent
Requires-Python: >=3.6
License-File: LICENSE
